{
  "video_title": "【雑談】筋肉系Vtuberと寝落ちもちもちしよ？♥初見さん大歓迎!!【#鎖乙女がぶ /#パレプロ研究生 】",
  "video_artist": "鎖乙女がぶ / Saotome Gabu 【パレプロ研究生】",
  "video_id": "crTeGx-62MM",
  "video_publish_date_str": "2025-12-01 12:31:58",
  "song_timeline": "【ノリノリ深夜お歌セトリ\uD83D\uDC3A\uD83D\uDC9C\uD83C\uDFB6】\n\n10:54 好きすぎて滅！ / M!LK\n16:33 倍倍FIGHT! / CANDY TUNE\n23:25 猫(ふんわりedition) / DISH&sol;&sol;\n30:14 さよならエレジー / 菅田将暉\n36:34 愛▽スクリ～ム！#{=サビのみ}/ AiScReam\n44:51 ラブソングに襲われる#{=サビのみ} / =LOVE\n49:11 とくべチュ、して#{=サビのみ}/ =LOVE\n\n楽しすぎ雑談とお歌ありがとう～！！\n深夜にいっぱい笑わせてくれてとても幸せほくほくで眠りに付けますzzz"
}