{
  "video_title": "【歌枠￤karaoke】バラード歌枠…ゆっくりしてって？【パレプロ/常磐カナメ】#shorts",
  "video_artist": "常磐カナメ -TOKIWA Kaname - パレプロ",
  "video_id": "m2Q9tU--M2M",
  "video_publish_date_str": "2024-05-19 22:10:33",
  "song_timeline": "セットリスト\n0:00:00 OP\r\n0:00:43 開始\r\n0:01:22 01.星が瞬くこんな夜に / Supercell\r\n0:08:19 02.晩餐歌 / tuki,\r\n0:15:39 03.チェリー / スピッツ\r\n0:21:04 04.アイネクライネ / 米津玄師\r\n0:26:25 05.あなたの夜が明けるまで / 傘村トータ\r\n0:31:32 06.Alice in 冷凍庫 / Orangestar\r\n0:37:18 07.ハロ／ハワユ / ナノウ\r\n0:44:52 08.ハイド・アンド・シーク / 19 -iku\r\n0:51:03 09.ニア / 夏代孝明\r\n0:55:29 10.ピエロ/ KEI\r\n1:01:53 11.rain stops, good-bye / におP\r\n1:07:20 バラードとは・歌い方の癖について\r\n1:12:06 12.ただ声一つ / ロクデナシ\r\n1:16:45 13.蛍の光/童謡\r\n1:22:36 14.うたかた花火 / Supercell\r\n1:28:36 離席・セブンのもちもちリングチョコ\r\n1:40:56 15.ヒッチコック / ヨルシカ\r\n1:45:07 16.灰色と青 / 米津玄師\r\n1:51:34 17.メルティランドナイトメア / はるまきごはん\r\n1:56:40 18.回る空うさぎ / Orangestar\r\n1:59:36 告知、スパチャ読み他\n\n\n\n歌枠ありがとうございました！\n\n晩餐歌、ロナちゃんの歌みたほんとに良かったのとてもわかりみだし、カナメちゃんのお歌も聴けて嬉しいですね…！\n初めて聴く曲も結構あったのですが、それぞれ良い曲で、ピエロやrain stops, good-byeとかかなり好きな感じの曲でした！"
}