{
  "video_title": "夏曲を歌います【パレプロ/常磐カナメ】",
  "video_artist": "常磐カナメ -TOKIWA Kaname - パレプロ",
  "video_id": "G8A9cYoALDc",
  "video_publish_date_str": "2025-08-16 18:08:34",
  "song_timeline": "セットリスト\r\n0:00:00 OP\r\n0:07:13 開始\r\n0:15:43 01.晴る#{=1番のみ} / ヨルシカ\r\n0:19:23 02.あの夏に咲け / ヨルシカ\r\n0:27:55 03.海へ / syh \r\n0:42:28 04.うたかた花火 / supercell\r\n1:05:48 05.魔法のない世界で生きるということ / ユルーカ研究所\r\n1:19:22 06.いのちの名前 / 木村弓\r\n1:31:31 07.忘れてください / ヨルシカ\r\n1:36:09 08.憂、燦々 / クリープハイプ\r\n1:58:29 09.八月、某、月明かり / ヨルシカ\r\n\n0:36:23 メンバーの印象語り1\n0:48:34 メンバーの印象語り2\n2:03:16 テトリス歌みた同時視聴\n2:05:58 告知，スパチャ読みなど\n\n\n\r\nおつかなめでした！\r\nとても夏感じるお歌たちでした！\r\nメンバーの良いところ語るの、メンバー間の仲の良さ感じられてもっと好きになっちゃいます！\r\n\r\n腰の不調は絶対後に引きずるので、まず病院で診てもらうのをお勧めします…！\r\nそこで問題なかったら整体とかを検討してみる形がよいかと思います。"
}