{
  "video_title": "【歌枠｜KARAOKE】オールジャンルで歌っていく！君はどの曲がすき？💗※知名度調査中【#パレプロ #香鳴ハノン】",
  "video_artist": "Hanon Ch. 香鳴ハノン【パレプロ】",
  "video_id": "F3mL5NTyQ7Y",
  "video_publish_date_str": "2026-06-13 21:18:44",
  "song_timeline": "Today's Set List \n0:00:00 OP\n0:05:03 はのは～\n\n0:07:27；0:11:02 エマ / go!go!vanillas\n0:13:09；0:16:56 Honto / Sumika\n0:20:58；0:24:49 Re:Re: / ASIAN KUNG-FU GENERATION\n0:27:56；0:32:33 ミラクル / miwa\n0:33:54；0:38:47 ヒカリへ / miwa\n0:40:36；0:44:36 踊れオーケストラ / YASUHIRO\n∟0:42:24 ｶﾞｼｬﾝ\n0:46:29；0:50:50 Over Over / 澁谷かのん\n0:58:57 助かる\n\n1:00:18；1:03:38 超最強 / 超ときめき♡宣伝部\n1:10:33；1:14:38 Lovers / Sumika\n1:20:42；1:25:49 感情電車 / 私立恵比寿中学\n1:26:56；1:31:22 ジャンプ / 私立恵比寿中学\n1:34:14；1:38:52 シンガロン・シンガソン / 私立恵比寿中学\n1:41:13；1:45:52 粛聖!! ロリ神レクイエム☆ / しぐれうい\n1:49:38；1:53:45 帰り道 / 加藤英美里\n1:57:11；2:00:43 少女A / 中森明菜\n\n2:04:32；2:08:32 DISCOTHEQUE / 水樹奈々\n2:13:01 yell / fono feat.香鳴ハノン #{=アカペラ 一部のみ}\n2:19:11；2:23:07 ハート型ウイルス / AKB48 #{=なうしんぎんぐに記載なし}\n2:24:45；2:28:31 となりのバナナ / AKB48\n2:29:44；2:32:43 ガラスの I LOVE YOU / AKB48\n2:35:53；2:39:24 初恋サイダー\n2:42:09；2:45:27 おねがいダーリン / ナナホシ管弦楽団\n2:53:16；2:57:45 明日も / MUSH&Co.\n\n3:01:25；3:05:33 君のバンド / コレサワ\n3:06:29；3:12:33 たばこ / コレサワ\n3:13:20；3:17:47 つよくなりたい / miwa\n3:21:08；3:25:16 如月アテンション / じん\n3:25:49；3:29:25 スイートマジック / ろん×Junky\n3:29:53；3:33:54 リテラチュア / 上田麗奈\n3:34:09 灰色のサーガ / ChouCho #{=途中まで}\n3:46:29 My Dream / 直樹美紀 #{=アカペラ 一部のみ}\n3:51:29；3:56:32 かくれんぼ / AliA\n\n3:58:24 スパチャ読み\n4:46:20 エンドカード　告知"
}