{
  "video_title": "【歌枠￤karaoke】六月六日なので食卓塩を買いました【パレプロ/常磐カナメ】",
  "video_artist": "常磐カナメ -TOKIWA Kaname - パレプロ",
  "video_id": "kPqKX1ss4X8",
  "video_publish_date_str": "2026-06-06 18:39:30",
  "song_timeline": "セットリスト\n0:00:00 OP\n0:01:59 01. 瞬間、シンフォニー。 / 40mP，かぐや (cv.夏吉ゆうこ)\n0:06:31 02. 心に穴が空いた / ヨルシカ\n0:11:35 03. だから僕は音楽を辞めた / ヨルシカ\n0:28:39 04. フォニイ / ツミキ\n0:35:10 05. 君の知らない物語 / supercell\n0:41:03 06. 銀色飛行船 / supercell\n0:48:20 07. 救世主 / 月詠み\n0:52:29 08. 花に雨を、君に歌を / 月詠み\n1:39:40 09. 初めての恋が終わる時 / supercell\n1:45:15 10. ホシアイ / レフティーモンスターP\n1:50:08 11. ミルククラウン・オン・ソーネチカ / ユジー\n1:53:55 12. ツギハギスタッカート / とあ\n1:58:09 13. 青春の現在地 / Palette Project\n2:02:01 告知・スパチャ読みなど"
}